LICENSE
MANIFEST.in
README.rst
requirements.txt
setup.cfg
setup.py
ckanext/__init__.py
ckanext/matomo/__init__.py
ckanext/matomo/cli.py
ckanext/matomo/commands.py
ckanext/matomo/helpers.py
ckanext/matomo/logic.py
ckanext/matomo/matomo_api.py
ckanext/matomo/model.py
ckanext/matomo/paster.py
ckanext/matomo/reports.py
ckanext/matomo/tracking.py
ckanext/matomo/plugin/__init__.py
ckanext/matomo/plugin/flask_plugin.py
ckanext/matomo/plugin/pylons_plugin.py
ckanext/matomo/public/javascript/chart-column.js
ckanext/matomo/public/javascript/chart-doughnut.js
ckanext/matomo/templates/base.html
ckanext/matomo/templates/matomo/snippets/matomo.html
ckanext/matomo/templates/report/analytics.html
ckanext/matomo/templates/report/dataset_analytics.html
ckanext/matomo/templates/report/location_analytics.html
ckanext/matomo/templates/report/option_last.html
ckanext/matomo/templates/report/option_time.html
ckanext/matomo/templates/report/organization_analytics.html
ckanext/matomo/templates/report/resource_analytics.html
ckanext/matomo/templates/report/search_term_analytics.html
ckanext/matomo/templates/report/snippets/entrances_percentage_td.html
ckanext/matomo/tests/__init__.py
ckanext/matomo/tests/test_plugin.py
ckanext_matomo.egg-info/PKG-INFO
ckanext_matomo.egg-info/SOURCES.txt
ckanext_matomo.egg-info/dependency_links.txt
ckanext_matomo.egg-info/entry_points.txt
ckanext_matomo.egg-info/namespace_packages.txt
ckanext_matomo.egg-info/top_level.txt