Metadata-Version: 2.1
Name: ckanext-matomo
Version: 0.0.1
Summary: Matomo analytics for CKAN
Home-page: https://github.com/vrk-kpa/ckanext-matomo
Author: Jari-Pekka Voutilainen
Author-email: jari-pekka.voutilainen@gofore.com
License: AGPL
Keywords: CKAN analytics matomo
Platform: UNKNOWN
Classifier: Development Status :: 4 - Beta
Classifier: License :: OSI Approved :: GNU Affero General Public License v3 or later (AGPLv3+)
Classifier: Programming Language :: Python :: 2.7
Classifier: Programming Language :: Python :: 3
License-File: LICENSE
